memestatus/core.py
memestatus/cpu.py
memestatus/disk.py
memestatus/mem.py
memestatus/uptime.py
memestatus-1.0.dist-info/DESCRIPTION.rst
memestatus-1.0.dist-info/METADATA
memestatus-1.0.dist-info/RECORD
memestatus-1.0.dist-info/WHEEL
memestatus-1.0.dist-info/metadata.json
memestatus-1.0.dist-info/top_level.txt
