Metadata-Version: 2.0
Name: memestatus
Version: 1.0
Summary: A library for parsing status.memework.org
Home-page: https://git.memework.org/lold/memestatus
Author: S Stewart
Author-email: iamtheworst@programmer.net
License: MIT
Download-URL: https://git.memework.org/lold/memestatus/archive/1.0.tar.gz
Keywords: forfun,memework,parsing
Platform: UNKNOWN
Requires-Dist: requests
